lucidscan/__init__.py
lucidscan/bootstrap/__init__.py
lucidscan/bootstrap/paths.py
lucidscan/bootstrap/platform.py
lucidscan/bootstrap/validation.py
lucidscan/bootstrap/versions.py
lucidscan/cli/__init__.py
lucidscan/cli/__main__.py
lucidscan/cli/arguments.py
lucidscan/cli/config_bridge.py
lucidscan/cli/exit_codes.py
lucidscan/cli/runner.py
lucidscan/cli/commands/__init__.py
lucidscan/cli/commands/autoconfigure.py
lucidscan/cli/commands/help.py
lucidscan/cli/commands/init.py
lucidscan/cli/commands/list_scanners.py
lucidscan/cli/commands/scan.py
lucidscan/cli/commands/serve.py
lucidscan/cli/commands/status.py
lucidscan/cli/commands/validate.py
lucidscan/config/__init__.py
lucidscan/config/ignore.py
lucidscan/config/loader.py
lucidscan/config/models.py
lucidscan/config/validation.py
lucidscan/core/__init__.py
lucidscan/core/domain_runner.py
lucidscan/core/git.py
lucidscan/core/logging.py
lucidscan/core/models.py
lucidscan/core/streaming.py
lucidscan/core/subprocess_runner.py
lucidscan/detection/__init__.py
lucidscan/detection/detector.py
lucidscan/detection/frameworks.py
lucidscan/detection/languages.py
lucidscan/detection/tools.py
lucidscan/generation/__init__.py
lucidscan/generation/config_generator.py
lucidscan/generation/package_installer.py
lucidscan/mcp/__init__.py
lucidscan/mcp/formatter.py
lucidscan/mcp/server.py
lucidscan/mcp/tools.py
lucidscan/mcp/watcher.py
lucidscan/pipeline/__init__.py
lucidscan/pipeline/executor.py
lucidscan/pipeline/parallel.py
lucidscan/plugins/__init__.py
lucidscan/plugins/discovery.py
lucidscan/plugins/coverage/__init__.py
lucidscan/plugins/coverage/base.py
lucidscan/plugins/coverage/coverage_py.py
lucidscan/plugins/coverage/istanbul.py
lucidscan/plugins/enrichers/__init__.py
lucidscan/plugins/enrichers/base.py
lucidscan/plugins/linters/__init__.py
lucidscan/plugins/linters/base.py
lucidscan/plugins/linters/biome.py
lucidscan/plugins/linters/checkstyle.py
lucidscan/plugins/linters/eslint.py
lucidscan/plugins/linters/ruff.py
lucidscan-0.5.13.dist-info/licenses/LICENSE
lucidscan-0.5.13.dist-info/METADATA
lucidscan-0.5.13.dist-info/WHEEL
lucidscan-0.5.13.dist-info/entry_points.txt
lucidscan-0.5.13.dist-info/top_level.txt
lucidscan-0.5.13.dist-info/RECORD
