Metadata-Version: 2.4
Name: lucidscan
Version: 0.5.13
Summary: LucidScan - The trust layer for AI-assisted development
Author-email: Voldeq GmbH <toni.antunovic@voldeq.com>
License: Apache-2.0
Keywords: security,scanner,devsecops,sast,sca,iac,container,vulnerability,trivy,semgrep,checkov,cli,mcp,ai,claude,cursor,linting,type-checking,testing,coverage
Classifier: Development Status :: 4 - Beta
Classifier: Environment :: Console
Classifier: Intended Audience :: Developers
Classifier: Intended Audience :: Information Technology
Classifier: Intended Audience :: System Administrators
Classifier: License :: OSI Approved :: Apache Software License
Classifier: Operating System :: MacOS
Classifier: Operating System :: POSIX :: Linux
Classifier: Programming Language :: Python :: 3
Classifier: Programming Language :: Python :: 3.10
Classifier: Programming Language :: Python :: 3.11
Classifier: Programming Language :: Python :: 3.12
Classifier: Topic :: Security
Classifier: Topic :: Software Development :: Quality Assurance
Classifier: Topic :: Software Development :: Testing
Classifier: Typing :: Typed
Requires-Python: >=3.10
License-File: LICENSE
Requires-Dist: PyYAML>=6.0
Requires-Dist: pathspec>=0.12.0
Requires-Dist: questionary>=2.0
Requires-Dist: Jinja2>=3.0
Requires-Dist: mcp>=1.0.0
Requires-Dist: watchdog>=4.0.0
Requires-Dist: defusedxml>=0.7.1
Requires-Dist: tomli>=2.0.0; python_version < "3.11"
Provides-Extra: dev
Requires-Dist: pytest>=7.0; extra == "dev"
Requires-Dist: pytest-asyncio>=0.23.0; extra == "dev"
Requires-Dist: mypy>=1.0; extra == "dev"
Requires-Dist: pyright>=1.1; extra == "dev"
Dynamic: license-file
